msilib/__init__.py
msilib/_msi.c
msilib/_msi.cp313-win_amd64.pyd
msilib/schema.py
msilib/sequence.py
msilib/text.py
msilib/include/_msi.h
msilib/include/pythoncapi_compat.h
python_msilib-0.5.0.dist-info/licenses/LICENSE
python_msilib-0.5.0.dist-info/METADATA
python_msilib-0.5.0.dist-info/WHEEL
python_msilib-0.5.0.dist-info/top_level.txt
python_msilib-0.5.0.dist-info/RECORD
