Metadata-Version: 2.4
Name: python-msilib
Version: 0.5.0
Summary: Read and write Microsoft Installer files
Author-email: Marcelo Duarte <marcelotduarte@users.noreply.github.com>, " Martin v. Löwis" <loewis@users.noreply.github.com>
License-Expression: PSF-2.0
Project-URL: Source, https://github.com/marcelotduarte/python-msilib
Project-URL: Changelog, https://github.com/marcelotduarte/python-msilib/releases
Project-URL: Documentation, https://docs.python.org/3.12/library/msilib.html
Keywords: msilib
Classifier: Development Status :: 5 - Production/Stable
Classifier: Intended Audience :: Developers
Classifier: Natural Language :: English
Classifier: Operating System :: OS Independent
Classifier: Programming Language :: C
Classifier: Programming Language :: Python
Classifier: Programming Language :: Python :: 3
Classifier: Programming Language :: Python :: 3 :: Only
Classifier: Programming Language :: Python :: 3.13
Classifier: Programming Language :: Python :: 3.14
Classifier: Programming Language :: Python :: Free Threading :: 2 - Beta
Classifier: Topic :: Software Development :: Build Tools
Classifier: Topic :: Software Development :: Libraries :: Python Modules
Classifier: Topic :: System :: Software Distribution
Classifier: Topic :: Utilities
Requires-Python: >=3.13
License-File: LICENSE
Provides-Extra: dev
Requires-Dist: bump-my-version==1.2.4; extra == "dev"
Requires-Dist: cibuildwheel==3.3.0; extra == "dev"
Requires-Dist: pre-commit==4.5.0; extra == "dev"
Provides-Extra: tests
Requires-Dist: coverage==7.12.0; extra == "tests"
Requires-Dist: pytest==9.0.2; extra == "tests"
Dynamic: license-file
